<CALLOUT>
	<GENERAL>
		<CALLOUTMESSAGE><![CDATA[Ukradené kolo]]></CALLOUTMESSAGE>
		<FURTHERINFORMATION><![CDATA[Bylo spatreno ~y~ukradené kolo~w~, zastavte jeho ridice.]]></FURTHERINFORMATION>
	</GENERAL>
	<OUTCOME0>
	</OUTCOME0>
	<OUTCOME1>
		<DIALOGUES>
			<DIALOGUE><![CDATA[~b~Ty:~w~ Dobrý den. Muzu se vás zeptat na pár kratsích otázek?]]></DIALOGUE>
			<DIALOGUE TARGET="M"><![CDATA[~r~Podezrelý:~w~ Jasne, pokracujte. Ale dávejte pozor na ten provoz za vámi. Pozor!]]></DIALOGUE>
			<DIALOGUE TARGET="F"><![CDATA[~r~Podezrelá:~w~ Jasne, pokracujte. Ale dávejte pozor na ten provoz za vámi. Pozor!]]></DIALOGUE>
		</DIALOGUES>
	</OUTCOME1>
	<OUTCOME2>
		<DIALOGUES>
			<DIALOGUE><![CDATA[~b~Ty:~w~ Dobrý den, muzeme si o tomto kole promluvit?]]></DIALOGUE>
			<DIALOGUE PLAYER="M" TARGET="M"><![CDATA[~r~Podezrelý:~w~ Co byste o nem chtel vedet?]]></DIALOGUE>
			<DIALOGUE PLAYER="M" TARGET="F"><![CDATA[~r~Podezrelá:~w~ Co byste o nem chtel vedet?]]></DIALOGUE>
			<DIALOGUE PLAYER="F" TARGET="M"><![CDATA[~r~Podezrelý:~w~ Co byste o nem chtela vedet?]]></DIALOGUE>
			<DIALOGUE PLAYER="F" TARGET="F"><![CDATA[~r~Podezrelá:~w~ Co byste o nem chtela vedet?]]></DIALOGUE>
			<DIALOGUE><![CDATA[~b~Ty:~w~ Bylo nahláseno jako odcizené, fakticky vzato dnes.]]></DIALOGUE>
			<DIALOGUE TARGET="M"><![CDATA[~r~Podezrelý:~w~ O, haha. Prominte, nahlásil jsem to já! Myslel jsem, ze jsem ho ztratil, ale nasel jsem ho!]]></DIALOGUE>
			<DIALOGUE TARGET="F"><![CDATA[~r~Podezrelá:~w~ O, haha. Prominte, nahlásila jsem to já! Myslela jsem, ze jsem ho ztratila, ale nasela jsem ho!]]></DIALOGUE>
			<DIALOGUE><![CDATA[~b~Ty:~w~ Chápu, takze toto kolo je registrované na vás?]]></DIALOGUE>
			<DIALOGUE TARGET="M"><![CDATA[~r~Podezrelý:~w~ Jo, naprosto. Provedte si klidne vsechny potrebné kontroly.]]></DIALOGUE>
			<DIALOGUE TARGET="F"><![CDATA[~r~Podezrelá:~w~ Jo, naprosto. Provedte si klidne vsechny potrebné kontroly.]]></DIALOGUE>
		</DIALOGUES>
	</OUTCOME2>
	<OUTCOME3>
		<NOTIFICATION><![CDATA[úzkostný]]></NOTIFICATION>
		<DIALOGUES>
			<DIALOGUE><![CDATA[~b~Ty:~w~ Dobrý den. Duvod, proc s vámi chci mluvit, je kvuli tomu kolu.]]></DIALOGUE>
			<DIALOGUE TARGET="M"><![CDATA[~r~Podezrelý:~w~ Snazím se nekam dostat. Pneumatika není prázdná, ani nic není rozbité. Tak co je spatne?]]></DIALOGUE>
			<DIALOGUE TARGET="F"><![CDATA[~r~Podezrelá:~w~ Snazím se nekam dostat. Pneumatika není prázdná, ani nic není rozbité. Tak co je spatne?]]></DIALOGUE>
			<DIALOGUE><![CDATA[~b~Ty:~w~ Vcera bylo nahláseno jako kradené.]]></DIALOGUE>
			<DIALOGUE TARGET="M"><![CDATA[~r~Podezrelý:~w~ Ou. Um, to je zvlástní.]]></DIALOGUE>
			<DIALOGUE TARGET="F"><![CDATA[~r~Podezrelá:~w~ Ou. Um, to je zvlástní.]]></DIALOGUE>
			<DIALOGUE TARGET="M"><![CDATA[~b~Ty:~w~ Nevedel byste proc?]]></DIALOGUE>
			<DIALOGUE TARGET="F"><![CDATA[~b~Ty:~w~ Nevedela byste proc?]]></DIALOGUE>
			<DIALOGUE TARGET="M"><![CDATA[~r~Podezrelý:~w~ Um...ano! Úplne jsem zapomnel, ze jsem ho nahlásil jako kradené.]]></DIALOGUE>
			<DIALOGUE TARGET="F"><![CDATA[~r~Podezrelá:~w~ Um...ano! Úplne jsem zapomnela, ze jsem ho nahlásila jako kradené.]]></DIALOGUE>
		</DIALOGUES>
	</OUTCOME3>	
	<OUTCOME4>
		<DIALOGUES>
			<DIALOGUE><![CDATA[~b~Ty:~w~ Dobrý den. Mohli bychom si trochu popovídat o tom kole?]]></DIALOGUE>
			<DIALOGUE TARGET="M"><![CDATA[~r~Podezrelý:~w~ No, muzeme.]]></DIALOGUE>
			<DIALOGUE TARGET="F"><![CDATA[~r~Podezrelá:~w~ No, muzeme.]]></DIALOGUE>
			<DIALOGUE><![CDATA[~b~Ty:~w~ V nasich záznamech bylo nedávno hláseno jako krádené.]]></DIALOGUE>
			<DIALOGUE TARGET="M"><![CDATA[~r~Podezrelý:~w~ ...]]></DIALOGUE>
			<DIALOGUE TARGET="F"><![CDATA[~r~Podezrelá:~w~ ...]]></DIALOGUE>
			<DIALOGUE TARGET="M"><![CDATA[~b~Ty:~w~ Prominte, co jste ríkal?]]></DIALOGUE>
			<DIALOGUE TARGET="F"><![CDATA[~b~Ty:~w~ Prominte, co jste ríkala?]]></DIALOGUE>
			<DIALOGUE TARGET="M"><![CDATA[~r~Podezrelý:~w~ K této veci se vyjadrovat nebudu.]]></DIALOGUE>
			<DIALOGUE TARGET="F"><![CDATA[~r~Podezrelá:~w~ K této veci se vyjadrovat nebudu.]]></DIALOGUE>
		</DIALOGUES>
	</OUTCOME4>	
	<OUTCOME5>
		<DIALOGUES>
			<DIALOGUE TARGET="M"><![CDATA[~r~Podezrelý:~w~ ARRGH! NÉ TY NE!]]></DIALOGUE>
			<DIALOGUE TARGET="F"><![CDATA[~r~Podezrelá:~w~ ARRGH! NÉ TY NE!]]></DIALOGUE>
		</DIALOGUES>
	</OUTCOME5>
</CALLOUT>


<!-- <![CDATA[]]> -->